{
  "id": "delete-project",
  "name": "删除项目",
  "level": 4,
  "parent": "project-crud",
  "children": [],
  "isLeaf": true,
  "summary": "删除项目 API。DELETE /api/projects/:id，从数据库中永久删除项目记录。",
  "specDetail": {
    "description": "API 端点 DELETE /api/projects/:id，通过 Prisma 删除指定 ID 的项目。",
    "parameters": [
      "API: DELETE /api/projects/:id",
      "成功响应: { success: true }",
      "失败响应: 404 { error: Project not found }"
    ]
  },
  "constraints": [
    "删除操作不可恢复",
    "项目不存在时返回 404"
  ],
  "acceptanceCriteria": [
    {
      "given": "项目存在",
      "when": "调用删除 API",
      "then": "项目从数据库中永久删除"
    }
  ],
  "testCases": {
    "unit-test": [],
    "end-to-end": [],
    "script-test": []
  },
  "status": "in-progress",
  "syncMeta": {
    "lastSyncAt": "2026-05-19T12:00:00Z",
    "baseCommit": "20df4fe",
    "baseCommitMessage": "feat(skill-e2e-testing): add Stage 6 summary report, boundary cases, pipeline diagram",
    "branch": "feature/specs-page",
    "sourceFiles": [
      "apps/server/src/routes/projects.ts"
    ]
  }
}
