{
  "id": "specs-list-view",
  "name": "Specs List View",
  "level": 4,
  "parent": "graph-visualization",
  "children": [],
  "isLeaf": true,
  "summary": "Tabular list view of spec nodes with filtering and sorting capabilities",
  "goals": [
    "Display spec nodes in a searchable, sortable list format",
    "Provide quick navigation to spec details from the list"
  ],
  "design": null,
  "specDetail": {
    "description": "A SpecsList component that renders spec nodes as a filterable, sortable table or card list. Shows node name, level, status, last sync date, and parent path. Supports search, filtering by status/level, and sorting by various fields.",
    "parameters": [
      { "name": "nodes", "type": "SpecNode[]", "description": "Array of spec nodes to display" },
      { "name": "filters", "type": "object", "description": "Active filters: status, level, domain, search text" },
      { "name": "sortField", "type": "string", "description": "Field to sort by (name, level, status, lastSyncAt)" },
      { "name": "onNodeSelect", "type": "function", "description": "Callback when a node row is clicked" }
    ]
  },
  "constraints": [
    "Must support filtering by status, level, and domain simultaneously",
    "Must update the list in real-time as filters are changed (debounced search)",
    "Must show the full parent path for each node (breadcrumb style)"
  ],
  "acceptanceCriteria": [
    {
      "given": "spec nodes exist across multiple domains and levels",
      "when": "the user applies a filter by domain",
      "then": "only nodes matching the selected domain are displayed with updated counts"
    }
  ],
  "status": "in-progress",
  "syncMeta": {
    "lastSyncAt": "2026-05-14T00:00:00Z",
    "baseCommit": "944b334",
    "baseCommitMessage": "docs(sync-specs): implement leaf determination redesign with frontend/backend criteria",
    "branch": "feature/specs-page",
    "sourceFiles": [
      "src/components/SpecsList.tsx"
    ]
  }
}
